Workbook

Sheet TRABAJOS
A1: GM7 PRO · CONTROL OPERATIVO DE TRABAJOS
A2: ID Trabajo | B2: Fecha Pedido | C2: Cliente | D2: Tipo Trabajo | E2: Descripción | F2: Cantidad | G2: ¿Trae Diseño? | H2: Costo Diseño | I2: Total Trabajo | J2: Anticipo 50% | K2: Anticipo Recibido | L2: Saldo Pendiente | M2: Responsable Diseño | N2: Fecha Compromiso | O2: Fecha Entrega Real | P2: Prioridad | Q2: Status | R2: Pago Completo | S2: Comentarios
A3: =IF(B3="","","FC-"&TEXT(ROW()-2,"0000")) | J3: =IF(I3="","",I3*0.5) | L3: =IF(I3="","",I3-K3) | R3: =IF(I3="","",IF(L3<=0,"Sí","No"))
A4: =IF(B4="","","FC-"&TEXT(ROW()-2,"0000")) | J4: =IF(I4="","",I4*0.5) | L4: =IF(I4="","",I4-K4) | R4: =IF(I4="","",IF(L4<=0,"Sí","No"))
A5: =IF(B5="","","FC-"&TEXT(ROW()-2,"0000")) | J5: =IF(I5="","",I5*0.5) | L5: =IF(I5="","",I5-K5) | R5: =IF(I5="","",IF(L5<=0,"Sí","No"))
A6: =IF(B6="","","FC-"&TEXT(ROW()-2,"0000")) | J6: =IF(I6="","",I6*0.5) | L6: =IF(I6="","",I6-K6) | R6: =IF(I6="","",IF(L6<=0,"Sí","No"))
A7: =IF(B7="","","FC-"&TEXT(ROW()-2,"0000")) | J7: =IF(I7="","",I7*0.5) | L7: =IF(I7="","",I7-K7) | R7: =IF(I7="","",IF(L7<=0,"Sí","No"))
A8: =IF(B8="","","FC-"&TEXT(ROW()-2,"0000")) | J8: =IF(I8="","",I8*0.5) | L8: =IF(I8="","",I8-K8) | R8: =IF(I8="","",IF(L8<=0,"Sí","No"))
A9: =IF(B9="","","FC-"&TEXT(ROW()-2,"0000")) | J9: =IF(I9="","",I9*0.5) | L9: =IF(I9="","",I9-K9) | R9: =IF(I9="","",IF(L9<=0,"Sí","No"))
A10: =IF(B10="","","FC-"&TEXT(ROW()-2,"0000")) | J10: =IF(I10="","",I10*0.5) | L10: =IF(I10="","",I10-K10) | R10: =IF(I10="","",IF(L10<=0,"Sí","No"))
A11: =IF(B11="","","FC-"&TEXT(ROW()-2,"0000")) | J11: =IF(I11="","",I11*0.5) | L11: =IF(I11="","",I11-K11) | R11: =IF(I11="","",IF(L11<=0,"Sí","No"))
A12: =IF(B12="","","FC-"&TEXT(ROW()-2,"0000")) | J12: =IF(I12="","",I12*0.5) | L12: =IF(I12="","",I12-K12) | R12: =IF(I12="","",IF(L12<=0,"Sí","No"))
A13: =IF(B13="","","FC-"&TEXT(ROW()-2,"0000")) | J13: =IF(I13="","",I13*0.5) | L13: =IF(I13="","",I13-K13) | R13: =IF(I13="","",IF(L13<=0,"Sí","No"))
A14: =IF(B14="","","FC-"&TEXT(ROW()-2,"0000")) | J14: =IF(I14="","",I14*0.5) | L14: =IF(I14="","",I14-K14) | R14: =IF(I14="","",IF(L14<=0,"Sí","No"))
... A202: =IF(B202="","","FC-"&TEXT(ROW()-2,"0000")) | J202: =IF(I202="","",I202*0.5) | L202: =IF(I202="","",I202-K202) | R202: =IF(I202="","",IF(L202<=0,"Sí","No"))
A203: TOTALES → | I203: =SUM(I3:I202) | J203: =SUM(J3:J202) | K203: =SUM(K3:K202) | L203: =SUM(L3:L202)

Sheet PAGOS
A1: GM7 PRO · ESTADO DE CUENTA Y PAGOS
A2: ID Trabajo | B2: Fecha Pedido | C2: Cliente | D2: Descripción | E2: Total Trabajo | F2: Anticipo Recibido | G2: Saldo Pendiente | H2: Estado Pago
A3: =IF(TRABAJOS!B3="","",TRABAJOS!A3) | B3: =IF(TRABAJOS!B3="","",TRABAJOS!B3) | C3: =IF(TRABAJOS!B3="","",TRABAJOS!C3) | D3: =IF(TRABAJOS!B3="","",TRABAJOS!E3) | E3: =IF(TRABAJOS!B3="","",TRABAJOS!I3) | F3: =IF(TRABAJOS!B3="","",TRABAJOS!K3) | G3: =IF(TRABAJOS!B3="","",TRABAJOS!L3) | H3: =IF(TRABAJOS!B3="","",IF(TRABAJOS!L3<=0,"Liquidado","Parcial"))
A4: =IF(TRABAJOS!B4="","",TRABAJOS!A4) | B4: =IF(TRABAJOS!B4="","",TRABAJOS!B4) | C4: =IF(TRABAJOS!B4="","",TRABAJOS!C4) | D4: =IF(TRABAJOS!B4="","",TRABAJOS!E4) | E4: =IF(TRABAJOS!B4="","",TRABAJOS!I4) | F4: =IF(TRABAJOS!B4="","",TRABAJOS!K4) | G4: =IF(TRABAJOS!B4="","",TRABAJOS!L4) | H4: =IF(TRABAJOS!B4="","",IF(TRABAJOS!L4<=0,"Liquidado","Parcial"))
A5: =IF(TRABAJOS!B5="","",TRABAJOS!A5) | B5: =IF(TRABAJOS!B5="","",TRABAJOS!B5) | C5: =IF(TRABAJOS!B5="","",TRABAJOS!C5) | D5: =IF(TRABAJOS!B5="","",TRABAJOS!E5) | E5: =IF(TRABAJOS!B5="","",TRABAJOS!I5) | F5: =IF(TRABAJOS!B5="","",TRABAJOS!K5) | G5: =IF(TRABAJOS!B5="","",TRABAJOS!L5) | H5: =IF(TRABAJOS!B5="","",IF(TRABAJOS!L5<=0,"Liquidado","Parcial"))
A6: =IF(TRABAJOS!B6="","",TRABAJOS!A6) | B6: =IF(TRABAJOS!B6="","",TRABAJOS!B6) | C6: =IF(TRABAJOS!B6="","",TRABAJOS!C6) | D6: =IF(TRABAJOS!B6="","",TRABAJOS!E6) | E6: =IF(TRABAJOS!B6="","",TRABAJOS!I6) | F6: =IF(TRABAJOS!B6="","",TRABAJOS!K6) | G6: =IF(TRABAJOS!B6="","",TRABAJOS!L6) | H6: =IF(TRABAJOS!B6="","",IF(TRABAJOS!L6<=0,"Liquidado","Parcial"))
A7: =IF(TRABAJOS!B7="","",TRABAJOS!A7) | B7: =IF(TRABAJOS!B7="","",TRABAJOS!B7) | C7: =IF(TRABAJOS!B7="","",TRABAJOS!C7) | D7: =IF(TRABAJOS!B7="","",TRABAJOS!E7) | E7: =IF(TRABAJOS!B7="","",TRABAJOS!I7) | F7: =IF(TRABAJOS!B7="","",TRABAJOS!K7) | G7: =IF(TRABAJOS!B7="","",TRABAJOS!L7) | H7: =IF(TRABAJOS!B7="","",IF(TRABAJOS!L7<=0,"Liquidado","Parcial"))
A8: =IF(TRABAJOS!B8="","",TRABAJOS!A8) | B8: =IF(TRABAJOS!B8="","",TRABAJOS!B8) | C8: =IF(TRABAJOS!B8="","",TRABAJOS!C8) | D8: =IF(TRABAJOS!B8="","",TRABAJOS!E8) | E8: =IF(TRABAJOS!B8="","",TRABAJOS!I8) | F8: =IF(TRABAJOS!B8="","",TRABAJOS!K8) | G8: =IF(TRABAJOS!B8="","",TRABAJOS!L8) | H8: =IF(TRABAJOS!B8="","",IF(TRABAJOS!L8<=0,"Liquidado","Parcial"))
A9: =IF(TRABAJOS!B9="","",TRABAJOS!A9) | B9: =IF(TRABAJOS!B9="","",TRABAJOS!B9) | C9: =IF(TRABAJOS!B9="","",TRABAJOS!C9) | D9: =IF(TRABAJOS!B9="","",TRABAJOS!E9) | E9: =IF(TRABAJOS!B9="","",TRABAJOS!I9) | F9: =IF(TRABAJOS!B9="","",TRABAJOS!K9) | G9: =IF(TRABAJOS!B9="","",TRABAJOS!L9) | H9: =IF(TRABAJOS!B9="","",IF(TRABAJOS!L9<=0,"Liquidado","Parcial"))
A10: =IF(TRABAJOS!B10="","",TRABAJOS!A10) | B10: =IF(TRABAJOS!B10="","",TRABAJOS!B10) | C10: =IF(TRABAJOS!B10="","",TRABAJOS!C10) | D10: =IF(TRABAJOS!B10="","",TRABAJOS!E10) | E10: =IF(TRABAJOS!B10="","",TRABAJOS!I10) | F10: =IF(TRABAJOS!B10="","",TRABAJOS!K10) | G10: =IF(TRABAJOS!B10="","",TRABAJOS!L10) | H10: =IF(TRABAJOS!B10="","",IF(TRABAJOS!L10<=0,"Liquidado","Parcial"))
A11: =IF(TRABAJOS!B11="","",TRABAJOS!A11) | B11: =IF(TRABAJOS!B11="","",TRABAJOS!B11) | C11: =IF(TRABAJOS!B11="","",TRABAJOS!C11) | D11: =IF(TRABAJOS!B11="","",TRABAJOS!E11) | E11: =IF(TRABAJOS!B11="","",TRABAJOS!I11) | F11: =IF(TRABAJOS!B11="","",TRABAJOS!K11) | G11: =IF(TRABAJOS!B11="","",TRABAJOS!L11) | H11: =IF(TRABAJOS!B11="","",IF(TRABAJOS!L11<=0,"Liquidado","Parcial"))
A12: =IF(TRABAJOS!B12="","",TRABAJOS!A12) | B12: =IF(TRABAJOS!B12="","",TRABAJOS!B12) | C12: =IF(TRABAJOS!B12="","",TRABAJOS!C12) | D12: =IF(TRABAJOS!B12="","",TRABAJOS!E12) | E12: =IF(TRABAJOS!B12="","",TRABAJOS!I12) | F12: =IF(TRABAJOS!B12="","",TRABAJOS!K12) | G12: =IF(TRABAJOS!B12="","",TRABAJOS!L12) | H12: =IF(TRABAJOS!B12="","",IF(TRABAJOS!L12<=0,"Liquidado","Parcial"))
A13: =IF(TRABAJOS!B13="","",TRABAJOS!A13) | B13: =IF(TRABAJOS!B13="","",TRABAJOS!B13) | C13: =IF(TRABAJOS!B13="","",TRABAJOS!C13) | D13: =IF(TRABAJOS!B13="","",TRABAJOS!E13) | E13: =IF(TRABAJOS!B13="","",TRABAJOS!I13) | F13: =IF(TRABAJOS!B13="","",TRABAJOS!K13) | G13: =IF(TRABAJOS!B13="","",TRABAJOS!L13) | H13: =IF(TRABAJOS!B13="","",IF(TRABAJOS!L13<=0,"Liquidado","Parcial"))
A14: =IF(TRABAJOS!B14="","",TRABAJOS!A14) | B14: =IF(TRABAJOS!B14="","",TRABAJOS!B14) | C14: =IF(TRABAJOS!B14="","",TRABAJOS!C14) | D14: =IF(TRABAJOS!B14="","",TRABAJOS!E14) | E14: =IF(TRABAJOS!B14="","",TRABAJOS!I14) | F14: =IF(TRABAJOS!B14="","",TRABAJOS!K14) | G14: =IF(TRABAJOS!B14="","",TRABAJOS!L14) | H14: =IF(TRABAJOS!B14="","",IF(TRABAJOS!L14<=0,"Liquidado","Parcial"))
... A202: =IF(TRABAJOS!B202="","",TRABAJOS!A202) | B202: =IF(TRABAJOS!B202="","",TRABAJOS!B202) | C202: =IF(TRABAJOS!B202="","",TRABAJOS!C202) | D202: =IF(TRABAJOS!B202="","",TRABAJOS!E202) | E202: =IF(TRABAJOS!B202="","",TRABAJOS!I202) | F202: =IF(TRABAJOS!B202="","",TRABAJOS!K202) | G202: =IF(TRABAJOS!B202="","",TRABAJOS!L202) | H202: =IF(TRABAJOS!B202="","",IF(TRABAJOS!L202<=0,"Liquidado","Parcial"))

Sheet DASHBOARD
A1: GM7 PRO · DASHBOARD EJECUTIVO | P1: Status | Q1: Cantidad
P2: Pendiente | Q2: =COUNTIF(TRABAJOS!Q3:Q202,"Pendiente")
A3: RESUMEN FINANCIERO | P3: En diseño | Q3: =COUNTIF(TRABAJOS!Q3:Q202,"En diseño")
A4: Total Ventas | B4: =SUM(TRABAJOS!I3:I202) | C4: Anticipos | D4: =SUM(TRABAJOS!K3:K202) | E4: Saldo Pendiente | F4: =SUM(TRABAJOS!L3:L202) | G4: Liquidados | H4: =COUNTIF(TRABAJOS!R3:R202,"Sí") | I4: Por Cobrar | J4: =COUNTIF(TRABAJOS!R3:R202,"No") | P4: En producción | Q4: =COUNTIF(TRABAJOS!Q3:Q202,"En producción")
P5: Listo para entrega | Q5: =COUNTIF(TRABAJOS!Q3:Q202,"Listo para entrega")
P6: Entregado | Q6: =COUNTIF(TRABAJOS!Q3:Q202,"Entregado")
A7: ESTADO DE PRODUCCIÓN | P7: Cancelado | Q7: =COUNTIF(TRABAJOS!Q3:Q202,"Cancelado")
A8: Pendientes | B8: =COUNTIF(TRABAJOS!Q3:Q202,"Pendiente") | C8: En Diseño | D8: =COUNTIF(TRABAJOS!Q3:Q202,"En diseño") | E8: En Producción | F8: =COUNTIF(TRABAJOS!Q3:Q202,"En producción") | G8: Listos | H8: =COUNTIF(TRABAJOS!Q3:Q202,"Listo para entrega") | I8: Entregados | J8: =COUNTIF(TRABAJOS!Q3:Q202,"Entregado")
P10: Pago | Q10: Cantidad
A11: DISEÑO Y PRIORIDADES | P11: Liquidado | Q11: =COUNTIF(TRABAJOS!R3:R202,"Sí")
A12: Trae Diseño | B12: =COUNTIF(TRABAJOS!G3:G202,"Sí") | C12: Requiere Diseño | D12: =COUNTIF(TRABAJOS!G3:G202,"No") | E12: Prioritarios | F12: =COUNTIF(TRABAJOS!P3:P202,"Prioritaria") | G12: Alta Prioridad | H12: =COUNTIF(TRABAJOS!P3:P202,"Alta") | I12: Total Trabajos | J12: =COUNTIF(TRABAJOS!B3:B202,"<>") | P12: Por cobrar | Q12: =COUNTIF(TRABAJOS!R3:R202,"No")
A14: DISTRIBUCIÓN OPERATIVA
P15: Semana | Q15: Ventas | R15: Pico | S15: Inicio | T15: Fin
P16: =TEXT(S16,"dd/mm") | Q16: =SUMIFS(TRABAJOS!$I$3:$I$202,TRABAJOS!$B$3:$B$202,">="&S16,TRABAJOS!$B$3:$B$202,"<="&T16) | R16: =IF(AND(Q16=MAX($Q$16:$Q$21),Q16>0),Q16,NA()) | S16: =TODAY()-WEEKDAY(TODAY(),2)+1-7*5 | T16: =S16+6
P17: =TEXT(S17,"dd/mm") | Q17: =SUMIFS(TRABAJOS!$I$3:$I$202,TRABAJOS!$B$3:$B$202,">="&S17,TRABAJOS!$B$3:$B$202,"<="&T17) | R17: =IF(AND(Q17=MAX($Q$16:$Q$21),Q17>0),Q17,NA()) | S17: =TODAY()-WEEKDAY(TODAY(),2)+1-7*4 | T17: =S17+6
P18: =TEXT(S18,"dd/mm") | Q18: =SUMIFS(TRABAJOS!$I$3:$I$202,TRABAJOS!$B$3:$B$202,">="&S18,TRABAJOS!$B$3:$B$202,"<="&T18) | R18: =IF(AND(Q18=MAX($Q$16:$Q$21),Q18>0),Q18,NA()) | S18: =TODAY()-WEEKDAY(TODAY(),2)+1-7*3 | T18: =S18+6
P19: =TEXT(S19,"dd/mm") | Q19: =SUMIFS(TRABAJOS!$I$3:$I$202,TRABAJOS!$B$3:$B$202,">="&S19,TRABAJOS!$B$3:$B$202,"<="&T19) | R19: =IF(AND(Q19=MAX($Q$16:$Q$21),Q19>0),Q19,NA()) | S19: =TODAY()-WEEKDAY(TODAY(),2)+1-7*2 | T19: =S19+6
P20: =TEXT(S20,"dd/mm") | Q20: =SUMIFS(TRABAJOS!$I$3:$I$202,TRABAJOS!$B$3:$B$202,">="&S20,TRABAJOS!$B$3:$B$202,"<="&T20) | R20: =IF(AND(Q20=MAX($Q$16:$Q$21),Q20>0),Q20,NA()) | S20: =TODAY()-WEEKDAY(TODAY(),2)+1-7*1 | T20: =S20+6
P21: =TEXT(S21,"dd/mm") | Q21: =SUMIFS(TRABAJOS!$I$3:$I$202,TRABAJOS!$B$3:$B$202,">="&S21,TRABAJOS!$B$3:$B$202,"<="&T21) | R21: =IF(AND(Q21=MAX($Q$16:$Q$21),Q21>0),Q21,NA()) | S21: =TODAY()-WEEKDAY(TODAY(),2)+1-7*0 | T21: =S21+6
P24: Mes | Q24: Ventas | S24: Inicio | T24: Fin
P25: =TEXT(S25,"mmm yy") | Q25: =SUMIFS(TRABAJOS!$I$3:$I$202,TRABAJOS!$B$3:$B$202,">="&S25,TRABAJOS!$B$3:$B$202,"<="&T25) | S25: =DATE(YEAR(TODAY()),MONTH(TODAY())-5,1) | T25: =EOMONTH(S25,0)
P26: =TEXT(S26,"mmm yy") | Q26: =SUMIFS(TRABAJOS!$I$3:$I$202,TRABAJOS!$B$3:$B$202,">="&S26,TRABAJOS!$B$3:$B$202,"<="&T26) | S26: =DATE(YEAR(TODAY()),MONTH(TODAY())-4,1) | T26: =EOMONTH(S26,0)
P27: =TEXT(S27,"mmm yy") | Q27: =SUMIFS(TRABAJOS!$I$3:$I$202,TRABAJOS!$B$3:$B$202,">="&S27,TRABAJOS!$B$3:$B$202,"<="&T27) | S27: =DATE(YEAR(TODAY()),MONTH(TODAY())-3,1) | T27: =EOMONTH(S27,0)
P28: =TEXT(S28,"mmm yy") | Q28: =SUMIFS(TRABAJOS!$I$3:$I$202,TRABAJOS!$B$3:$B$202,">="&S28,TRABAJOS!$B$3:$B$202,"<="&T28) | S28: =DATE(YEAR(TODAY()),MONTH(TODAY())-2,1) | T28: =EOMONTH(S28,0)
P29: =TEXT(S29,"mmm yy") | Q29: =SUMIFS(TRABAJOS!$I$3:$I$202,TRABAJOS!$B$3:$B$202,">="&S29,TRABAJOS!$B$3:$B$202,"<="&T29) | S29: =DATE(YEAR(TODAY()),MONTH(TODAY())-1,1) | T29: =EOMONTH(S29,0)
P30: =TEXT(S30,"mmm yy") | Q30: =SUMIFS(TRABAJOS!$I$3:$I$202,TRABAJOS!$B$3:$B$202,">="&S30,TRABAJOS!$B$3:$B$202,"<="&T30) | S30: =DATE(YEAR(TODAY()),MONTH(TODAY())-0,1) | T30: =EOMONTH(S30,0)
A32: TENDENCIA DE VENTAS (SEMANAL)
A50: RESUMEN MENSUAL DE VENTAS

Sheet DATOS_EMPRESA
A1: GM7 PRO · DATOS DE LA EMPRESA
A2: Campo | B2: Valor
A3: Nombre empresa | B3: GM7 Impresión Profesional
A4: Razón social | B4: GM7 Servicios Gráficos SA de CV
A5: RFC | B5: GM701010ABC
A6: Teléfono | B6: 33 1234 5678
A7: Correo | B7: contacto@gm7.com
A8: Dirección | B8: Guadalajara, Jalisco
A9: Mensaje cotización | B9: Vigencia de 15 días naturales.
A10: Mensaje recibo | B10: Gracias por su preferencia.
A11: Logo | B11: Pendiente de integración
